odoo/addons/event_min_seat/README.rst
odoo/addons/event_min_seat/__init__.py
odoo/addons/event_min_seat/__manifest__.py
odoo/addons/event_min_seat/i18n/es.po
odoo/addons/event_min_seat/i18n/event_min_seat.pot
odoo/addons/event_min_seat/i18n/it.po
odoo/addons/event_min_seat/models/__init__.py
odoo/addons/event_min_seat/models/event_event.py
odoo/addons/event_min_seat/models/event_type.py
odoo/addons/event_min_seat/readme/CONTRIBUTORS.md
odoo/addons/event_min_seat/readme/DESCRIPTION.md
odoo/addons/event_min_seat/static/description/icon.png
odoo/addons/event_min_seat/static/description/index.html
odoo/addons/event_min_seat/tests/__init__.py
odoo/addons/event_min_seat/tests/test_event_min_seat.py
odoo/addons/event_min_seat/views/event_event_views.xml
odoo/addons/event_min_seat/views/event_type_views.xml
odoo_addon_event_min_seat-18.0.1.0.0.2.dist-info/METADATA
odoo_addon_event_min_seat-18.0.1.0.0.2.dist-info/WHEEL
odoo_addon_event_min_seat-18.0.1.0.0.2.dist-info/top_level.txt
odoo_addon_event_min_seat-18.0.1.0.0.2.dist-info/RECORD
